deform_autoneed
