Metadata-Version: 1.0
Name: deform-autoneed
Version: 0.2.2b
Summary: Auto include resources in deform via Fanstatic.
Home-page: https://github.com/robinharms/deform_autoneed
Author: Robin Harms Oredsson
Author-email: robin@betahaus.net
License: UNKNOWN
Keywords: web colander deform fanstatic
Platform: UNKNOWN
Classifier: Programming Language :: Python
Classifier: Intended Audience :: Developers
Classifier: Topic :: Internet :: WWW/HTTP
Classifier: Topic :: Internet :: WWW/HTTP :: WSGI :: Application
Classifier: Development Status :: 4 - Beta
Classifier: License :: OSI Approved :: GNU General Public License v3 or later (GPLv3+)
Classifier: Programming Language :: Python :: 2.7
Classifier: Programming Language :: Python :: 3
